MANIFEST.in
NEWS.txt
README.rst
setup.py
src/ssmrandom/__init__.py
src/ssmrandom/pidfile.py
src/ssmrandom.egg-info/PKG-INFO
src/ssmrandom.egg-info/SOURCES.txt
src/ssmrandom.egg-info/dependency_links.txt
src/ssmrandom.egg-info/entry_points.txt
src/ssmrandom.egg-info/namespace_packages.txt
src/ssmrandom.egg-info/not-zip-safe
src/ssmrandom.egg-info/requires.txt
src/ssmrandom.egg-info/top_level.txt