Metadata-Version: 1.1
Name: ssmrandom
Version: 0.3
Summary: Entropy distribution using SSM (source-specific multicast)
Home-page: https://github.com/leifj/ssmrandom
Author: Leif Johansson
Author-email: leifj@sunet.se
License: BSD
Platform: UNKNOWN
Classifier: License :: OSI Approved
Classifier: License :: OSI Approved :: BSD License
Classifier: Programming Language :: Python
